render_engine_pagefind/__init__.py
render_engine_pagefind/plugin.py
render_engine_pagefind/theme.py
render_engine_pagefind/templates/pagefind.html
render_engine_pagefind-2024.1.1b1.dist-info/METADATA
render_engine_pagefind-2024.1.1b1.dist-info/WHEEL
render_engine_pagefind-2024.1.1b1.dist-info/top_level.txt
render_engine_pagefind-2024.1.1b1.dist-info/RECORD
